victron_mqtt/__init__.py
victron_mqtt/_unwrappers.py
victron_mqtt/_victron_enums.py
victron_mqtt/_victron_formulas.py
victron_mqtt/_victron_topics.py
victron_mqtt/constants.py
victron_mqtt/data_classes.py
victron_mqtt/device.py
victron_mqtt/formula_common.py
victron_mqtt/formula_metric.py
victron_mqtt/hub.py
victron_mqtt/id_utils.py
victron_mqtt/metric.py
victron_mqtt/writable_formula_metric.py
victron_mqtt/writable_metric.py
victron_mqtt/testing/__init__.py
victron_mqtt/testing/hub_helpers.py
victron_mqtt/utils/__init__.py
victron_mqtt/utils/dumb_mqtt_listener.py
victron_mqtt/utils/dump_mqtt.py
victron_mqtt/utils/dump_victron_mqtt.py
victron_mqtt/utils/view_metrics.py
victron_mqtt-2026.1.8.dist-info/METADATA
victron_mqtt-2026.1.8.dist-info/WHEEL
victron_mqtt-2026.1.8.dist-info/licenses/LICENSE
victron_mqtt-2026.1.8.dist-info/RECORD
