Metadata-Version: 2.4
Name: victron_mqtt
Version: 2026.1.8
Summary: Python library for communicating with Victron Venus OS MQTT interface
Project-URL: Documentation, https://github.com/tomer-w/victron_mqtt#readme
Project-URL: Issues, https://github.com/tomer-w/victron_mqtt/issues
Project-URL: Source, https://github.com/tomer-w/victron_mqtt
Author-email: Tomer <57483589+tomer-w@users.noreply.github.com>
License-Expression: MIT
License-File: LICENSE
Keywords: mqtt,venus os,victron
Classifier: Development Status :: 4 - Beta
Classifier: Programming Language :: Python
Classifier: Programming Language :: Python :: 3.9
Classifier: Programming Language :: Python :: 3.10
Classifier: Programming Language :: Python :: 3.11
Classifier: Programming Language :: Python :: Implementation :: CPython
Classifier: Programming Language :: Python :: Implementation :: PyPy
Requires-Python: >=3.9
Requires-Dist: paho-mqtt>=1.6.1
